snowpy3/Connection.py
snowpy3/SNOWPY3.py
snowpy3/Utils.py
snowpy3/__init__.py
snowpy3-2025.9.12.2.dist-info/METADATA
snowpy3-2025.9.12.2.dist-info/WHEEL
snowpy3-2025.9.12.2.dist-info/licenses/LICENSE
snowpy3-2025.9.12.2.dist-info/RECORD
