Metadata-Version: 2.4
Name: snowpy3
Version: 2025.9.12.2
Summary: Python 3 Library to interact with and manage a ServiceNow instance via JSONv2
Author-email: TANGONINE <snowpy3@tangonine.com>
Maintainer-email: TANGONINE <snowpy3@tangonine.com>
License: GPL-3.0-or-later
License-File: LICENSE
Keywords: api,change,incident,jsonv2,problem,servicenow,snow
Classifier: Development Status :: 5 - Production/Stable
Classifier: Intended Audience :: Developers
Classifier: License :: OSI Approved :: GNU General Public License v3 or later (GPLv3+)
Classifier: Operating System :: OS Independent
Classifier: Programming Language :: Python :: 3
Classifier: Programming Language :: Python :: 3.12
Classifier: Programming Language :: Python :: 3.13
Classifier: Topic :: Internet :: WWW/HTTP :: Dynamic Content
Classifier: Topic :: Software Development :: Libraries :: Python Modules
Classifier: Topic :: System :: Systems Administration
Requires-Python: >=3.12
Requires-Dist: redis>=6.4.0
Requires-Dist: requests>=2.32.5
